{   
    "params_provider": {
            "provider_name": "DepthOneScanTrainer",
            "provider_init": {
                "evaluator": "EfficientDepthOneEvaluator",
                "evaluator_init": {},
                "parameter_ranges": [
                    [
                        0,
                        3.1456
                    ],
                    [
                        0,
                        3.1456
                    ]
                ],
                "num_points": 15
            }
        },
    "pipeline_components": [
        {
            "component_name": "RecursiveTransitionStates",
            "component_init": {
                "trainer": "ScipyTrainer",
                "trainer_init": {
                    "evaluator": "MPSEvaluator",
                    "evaluator_init": {
                        "use_vidal_form": "True",
                        "use_swap_strategy": "True"
                    },
                    "minimize_args": {
                        "options": {
                            "maxiter": 20,
                            "rhobeg": 0.2
                        }
                    }
                }, 
                "reps": 3
            },
            "save_file": "method_7.json"
        }
    ],
    "description": "Recursive Transition States Trainer (p=3)"

}
